duallog/__init__.py
duallog/duallog.py
duallog-0.20.dist-info/LICENSE
duallog-0.20.dist-info/METADATA
duallog-0.20.dist-info/WHEEL
duallog-0.20.dist-info/top_level.txt
duallog-0.20.dist-info/RECORD
