Metadata-Version: 2.1
Name: duallog
Version: 0.20
Summary: Parallel logging to console and logfile
Home-page: https://github.com/acschaefer/duallog
Author: Alexander Schaefer
Author-email: acschaefer@users.noreply.github.com
Maintainer: Alexander Schaefer
License: MIT
Platform: UNKNOWN
Classifier: License :: OSI Approved :: MIT License
Classifier: Programming Language :: Python :: 2
Classifier: Programming Language :: Python :: 2.6
Classifier: Programming Language :: Python :: 2.7
Classifier: Programming Language :: Python :: 3
Classifier: Programming Language :: Python :: 3.3
Classifier: Programming Language :: Python :: 3.4
Classifier: Programming Language :: Python :: 3.5
Classifier: Programming Language :: Python :: 3.6
Classifier: Programming Language :: Python :: 3.7
Classifier: Operating System :: OS Independent
